{"chunk_definitions":[{"row":14,"row_count":1,"visible":true,"expansion_state":0,"options":{"engine":"r","label":"unnamed-chunk-23"},"document_id":"4FEE7064","chunk_id":"cz0oedtckmmni","chunk_label":"unnamed-chunk-1"},{"row":20,"row_count":1,"visible":true,"expansion_state":0,"options":{"engine":"r","label":"unnamed-chunk-24"},"document_id":"4FEE7064","chunk_id":"cyxqip4dq8g7l","chunk_label":"unnamed-chunk-2"},{"row":29,"row_count":1,"visible":true,"expansion_state":0,"options":{"engine":"r","label":"unnamed-chunk-25"},"document_id":"4FEE7064","chunk_id":"cunndbrbz08ji","chunk_label":"unnamed-chunk-3"},{"row":37,"row_count":1,"visible":true,"expansion_state":0,"options":{"engine":"r","label":"unnamed-chunk-26"},"document_id":"4FEE7064","chunk_id":"cbjq30aqlcngz","chunk_label":"unnamed-chunk-4"},{"row":44,"row_count":1,"visible":true,"expansion_state":0,"options":{"engine":"r","label":"unnamed-chunk-27"},"document_id":"4FEE7064","chunk_id":"cpnnvnodo2uex","chunk_label":"unnamed-chunk-5"},{"row":49,"row_count":1,"visible":true,"expansion_state":0,"options":{"engine":"r","label":"unnamed-chunk-28"},"document_id":"4FEE7064","chunk_id":"c8mijfji9t366","chunk_label":"unnamed-chunk-6"},{"row":58,"row_count":1,"visible":true,"expansion_state":0,"options":{"engine":"r","label":"unnamed-chunk-29"},"document_id":"4FEE7064","chunk_id":"cri01rotwaz07","chunk_label":"unnamed-chunk-7"},{"row":66,"row_count":1,"visible":true,"expansion_state":0,"options":{"engine":"r","label":"unnamed-chunk-30"},"document_id":"4FEE7064","chunk_id":"c1z59vdiwv37t","chunk_label":"unnamed-chunk-8"}],"doc_write_time":1643054023}