{"chunk_definitions":[{"row":9,"row_count":1,"visible":true,"expansion_state":0,"options":{"engine":"r","label":"unnamed-chunk-13"},"document_id":"08366A26","chunk_id":"cwxcnq3v09bxh","chunk_label":"unnamed-chunk-1"},{"row":14,"row_count":1,"visible":true,"expansion_state":0,"options":{"engine":"r","label":"unnamed-chunk-1"},"document_id":"08366A26","chunk_id":"c8z7q4c1jkb88","chunk_label":"unnamed-chunk-2"},{"row":18,"row_count":1,"visible":true,"expansion_state":0,"options":{"engine":"r","label":"unnamed-chunk-2"},"document_id":"08366A26","chunk_id":"co3l8w105o4hk","chunk_label":"unnamed-chunk-3"},{"row":24,"row_count":1,"visible":true,"expansion_state":0,"options":{"engine":"r","label":"unnamed-chunk-3"},"document_id":"08366A26","chunk_id":"cbc7fn3ic2a1l","chunk_label":"unnamed-chunk-4"},{"row":28,"row_count":1,"visible":true,"expansion_state":0,"options":{"engine":"r","label":"unnamed-chunk-4"},"document_id":"08366A26","chunk_id":"cah37y4rostxp","chunk_label":"unnamed-chunk-5"},{"row":33,"row_count":1,"visible":true,"expansion_state":0,"options":{"engine":"r","label":"unnamed-chunk-5"},"document_id":"08366A26","chunk_id":"cyzp98cgqdysz","chunk_label":"unnamed-chunk-6"},{"row":39,"row_count":1,"visible":true,"expansion_state":0,"options":{"engine":"r","label":"unnamed-chunk-6"},"document_id":"08366A26","chunk_id":"c97plgbl6x89z","chunk_label":"unnamed-chunk-7"},{"row":46,"row_count":1,"visible":true,"expansion_state":0,"options":{"engine":"r","label":"unnamed-chunk-7"},"document_id":"08366A26","chunk_id":"cht0obn737x1o","chunk_label":"unnamed-chunk-8"},{"row":52,"row_count":1,"visible":true,"expansion_state":0,"options":{"engine":"r","label":"unnamed-chunk-8"},"document_id":"08366A26","chunk_id":"c8ttjwwwzqo2u","chunk_label":"unnamed-chunk-9"},{"row":59,"row_count":1,"visible":true,"expansion_state":0,"options":{"engine":"r","label":"unnamed-chunk-9"},"document_id":"08366A26","chunk_id":"cx3g3bp0dja3s","chunk_label":"unnamed-chunk-10"},{"row":64,"row_count":1,"visible":true,"expansion_state":0,"options":{"engine":"r","label":"unnamed-chunk-10"},"document_id":"08366A26","chunk_id":"cqc75f2e7qx41","chunk_label":"unnamed-chunk-11"}],"doc_write_time":1739986789}