{"chunk_definitions":[{"row":16,"row_count":1,"visible":true,"expansion_state":0,"options":{"engine":"r","label":"unnamed-chunk-9"},"document_id":"4CAF0FA1","chunk_id":"cv06sya3995st","chunk_label":"unnamed-chunk-3"},{"row":23,"row_count":1,"visible":true,"expansion_state":0,"options":{"engine":"r","label":"unnamed-chunk-11"},"document_id":"4CAF0FA1","chunk_id":"c7wstwf2xm2pe","chunk_label":"unnamed-chunk-4"},{"row":40,"row_count":1,"visible":true,"expansion_state":0,"options":{"engine":"r","label":"unnamed-chunk-19"},"document_id":"4CAF0FA1","chunk_id":"cbezeqyd40lor","chunk_label":"unnamed-chunk-5"},{"row":47,"row_count":1,"visible":true,"expansion_state":0,"options":{"engine":"r","label":"unnamed-chunk-44"},"document_id":"4CAF0FA1","chunk_id":"cf5oxul1sbhw9","chunk_label":"unnamed-chunk-6"}],"doc_write_time":1641999009}