{"chunk_definitions":[{"chunk_id":"c6uj9tb2o84dw","expansion_state":0,"options":[],"row":17,"row_count":1,"visible":true},{"chunk_id":"c41wixbyhq1k2","expansion_state":0,"options":[],"row":29,"row_count":1,"visible":true},{"chunk_id":"c6ojyb45x6zt3","expansion_state":0,"options":[],"row":41,"row_count":1,"visible":true},{"chunk_id":"ccm29rjq642ju","expansion_state":0,"options":[],"row":48,"row_count":1,"visible":true},{"chunk_id":"c6c9dun1hu9i1","expansion_state":0,"options":[],"row":85,"row_count":1,"visible":true},{"chunk_id":"ck6k9g8g61gmy","expansion_state":0,"options":[],"row":101,"row_count":1,"visible":true},{"chunk_id":"cio1g9mesujg6","expansion_state":0,"options":[],"row":115,"row_count":1,"visible":true},{"chunk_id":"cjjo1acoo73vv","expansion_state":0,"options":[],"row":136,"row_count":1,"visible":true},{"chunk_id":"c3my4sxm00f9e","expansion_state":0,"options":[],"row":151,"row_count":1,"visible":true},{"chunk_id":"cwy4fxtgtqrpy","expansion_state":0,"options":[],"row":166,"row_count":1,"visible":true},{"chunk_id":"cz9jkdy7cw5w3","expansion_state":0,"options":[],"row":186,"row_count":1,"visible":true},{"chunk_id":"cu6d1lp3ihh6p","expansion_state":0,"options":[],"row":204,"row_count":1,"visible":true},{"chunk_id":"cng9zcf1usfxu","expansion_state":0,"options":[],"row":236,"row_count":1,"visible":true},{"chunk_id":"cwle0hjxotjw7","expansion_state":0,"options":[],"row":250,"row_count":1,"visible":true},{"chunk_id":"ch0uhxiicduxy","expansion_state":0,"options":[],"row":255,"row_count":1,"visible":true},{"chunk_id":"cg9sqzomhv2q6","expansion_state":0,"options":[],"row":266,"row_count":1,"visible":true},{"chunk_id":"ce1vp3uznrxb3","expansion_state":0,"options":[],"row":270,"row_count":1,"visible":true},{"chunk_id":"cf1susjeev85y","expansion_state":0,"options":[],"row":286,"row_count":1,"visible":true},{"chunk_id":"c4bo5oey119ba","expansion_state":0,"options":[],"row":298,"row_count":1,"visible":true},{"chunk_id":"c4aqater10zj2","expansion_state":0,"options":[],"row":310,"row_count":1,"visible":true}],"doc_write_time":1577396476.56303}
