{"chunk_definitions":[{"row":31,"row_count":1,"visible":true,"expansion_state":0,"options":{"engine":"r","label":"unnamed-chunk-5"},"document_id":"C6C4E8E6","chunk_id":"cy1csuhxym6co","chunk_label":"unnamed-chunk-3"},{"row":38,"row_count":1,"visible":true,"expansion_state":0,"options":{"engine":"r","label":"unnamed-chunk-10"},"document_id":"C6C4E8E6","chunk_id":"c5w61k3gqgzq7","chunk_label":"unnamed-chunk-4"},{"row":67,"row_count":1,"visible":true,"expansion_state":0,"options":{"engine":"r","label":"unnamed-chunk-2"},"document_id":"C6C4E8E6","chunk_id":"cb9takjociybz","chunk_label":"unnamed-chunk-7"},{"row":70,"row_count":1,"visible":true,"expansion_state":0,"options":{"engine":"r","label":"unnamed-chunk-3"},"document_id":"C6C4E8E6","chunk_id":"cqy8d2phgchfa","chunk_label":"unnamed-chunk-8"},{"row":74,"row_count":1,"visible":true,"expansion_state":0,"options":{"engine":"r","label":"unnamed-chunk-6"},"document_id":"C6C4E8E6","chunk_id":"ctefen3v2rt2m","chunk_label":"unnamed-chunk-9"},{"row":86,"row_count":1,"visible":true,"expansion_state":0,"options":{"engine":"r","label":"unnamed-chunk-10"},"document_id":"C6C4E8E6","chunk_id":"c0xsbxklnodty","chunk_label":"unnamed-chunk-10"},{"row":95,"row_count":1,"visible":true,"expansion_state":0,"options":{"engine":"r","label":"unnamed-chunk-25"},"document_id":"C6C4E8E6","chunk_id":"csb516wgq07nh","chunk_label":"unnamed-chunk-11"},{"row":99,"row_count":1,"visible":true,"expansion_state":0,"options":{"engine":"r","label":"unnamed-chunk-29"},"document_id":"C6C4E8E6","chunk_id":"c7hn3kugel0a3","chunk_label":"unnamed-chunk-12"},{"row":104,"row_count":1,"visible":true,"expansion_state":0,"options":{"engine":"r","label":"unnamed-chunk-30"},"document_id":"C6C4E8E6","chunk_id":"cm55d91nvuzdc","chunk_label":"unnamed-chunk-13"},{"row":108,"row_count":1,"visible":true,"expansion_state":0,"options":{"engine":"r","label":"unnamed-chunk-35"},"document_id":"C6C4E8E6","chunk_id":"cdf3x72bf0auw","chunk_label":"unnamed-chunk-14"},{"row":117,"row_count":1,"visible":true,"expansion_state":0,"options":{"engine":"r","label":"unnamed-chunk-39"},"document_id":"C6C4E8E6","chunk_id":"ck4q2a9gq2jp6","chunk_label":"unnamed-chunk-15"},{"row":127,"row_count":1,"visible":true,"expansion_state":0,"options":{"engine":"r","label":"unnamed-chunk-4"},"document_id":"C6C4E8E6","chunk_id":"cxccxv4kd9l96","chunk_label":"unnamed-chunk-16"},{"row":135,"row_count":1,"visible":true,"expansion_state":0,"options":{"engine":"r","label":"unnamed-chunk-5"},"document_id":"C6C4E8E6","chunk_id":"cwe0slyteyn01","chunk_label":"unnamed-chunk-17"},{"row":161,"row_count":1,"visible":true,"expansion_state":0,"options":{"engine":"r","label":"unnamed-chunk-6"},"document_id":"C6C4E8E6","chunk_id":"c8bvv5cxmtcip","chunk_label":"unnamed-chunk-18"},{"row":165,"row_count":1,"visible":true,"expansion_state":0,"options":{"engine":"r","label":"unnamed-chunk-7"},"document_id":"C6C4E8E6","chunk_id":"c90h2z5in0bl5","chunk_label":"unnamed-chunk-19"}],"doc_write_time":1641161442,"chunk_rendered_width":700}