{"chunk_definitions":[{"row":22,"row_count":1,"visible":true,"expansion_state":0,"options":{"engine":"r","label":"unnamed-chunk-1"},"document_id":null,"chunk_id":"cku5oqpo67vj1","chunk_label":"unnamed-chunk-1"},{"row":27,"row_count":1,"visible":true,"expansion_state":0,"options":{"engine":"r","label":"unnamed-chunk-2"},"document_id":null,"chunk_id":"c4ap1dledlzmt","chunk_label":"unnamed-chunk-2"},{"row":32,"row_count":1,"visible":true,"expansion_state":0,"options":[],"document_id":null,"chunk_id":"cbvz47tdq5j2b","chunk_label":"unnamed-chunk-3"},{"row":35,"row_count":1,"visible":true,"expansion_state":0,"options":{"engine":"r","label":"unnamed-chunk-1"},"document_id":"BB49D7F4","chunk_id":"cayfmyy7hd3ge","chunk_label":"unnamed-chunk-4"},{"row":39,"row_count":1,"visible":true,"expansion_state":0,"options":{"engine":"r","label":"unnamed-chunk-2"},"document_id":"BB49D7F4","chunk_id":"cqf9fxxwsbq3k","chunk_label":"unnamed-chunk-5"},{"row":55,"row_count":1,"visible":true,"expansion_state":0,"options":[],"document_id":null,"chunk_id":"crqwjwz1o620i","chunk_label":"unnamed-chunk-6"},{"row":59,"row_count":1,"visible":true,"expansion_state":0,"options":{"engine":"r","label":"unnamed-chunk-6"},"document_id":null,"chunk_id":"cnffwqkwgzk8t","chunk_label":"unnamed-chunk-7"},{"row":64,"row_count":1,"visible":true,"expansion_state":0,"options":[],"document_id":null,"chunk_id":"clcab9o63eaw1","chunk_label":"unnamed-chunk-8"},{"row":76,"row_count":1,"visible":true,"expansion_state":0,"options":[],"document_id":null,"chunk_id":"c8r8gnudtulci","chunk_label":"unnamed-chunk-9"},{"row":92,"row_count":1,"visible":true,"expansion_state":0,"options":[],"document_id":null,"chunk_id":"c62to469yw4jj","chunk_label":"unnamed-chunk-10"},{"row":107,"row_count":1,"visible":true,"expansion_state":0,"options":[],"document_id":null,"chunk_id":"ckik3uxlw2yd7","chunk_label":"unnamed-chunk-11"},{"row":124,"row_count":1,"visible":true,"expansion_state":0,"options":{"engine":"r","label":"unnamed-chunk-4"},"document_id":null,"chunk_id":"cky2haxke5o46","chunk_label":"unnamed-chunk-12"},{"row":140,"row_count":1,"visible":true,"expansion_state":0,"options":[],"document_id":null,"chunk_id":"coc0ya7e3989z","chunk_label":"unnamed-chunk-13"},{"row":143,"row_count":1,"visible":true,"expansion_state":0,"options":[],"document_id":null,"chunk_id":"cbw9b37jkqnh2","chunk_label":"unnamed-chunk-14"},{"row":155,"row_count":1,"visible":true,"expansion_state":0,"options":[],"document_id":null,"chunk_id":"c0taamtek8g0x","chunk_label":"unnamed-chunk-15"},{"row":166,"row_count":1,"visible":true,"expansion_state":0,"options":[],"document_id":null,"chunk_id":"cbrxkjgirhatn","chunk_label":"unnamed-chunk-16"},{"row":173,"row_count":1,"visible":true,"expansion_state":0,"options":[],"document_id":null,"chunk_id":"cfojgl6kjtggj","chunk_label":"unnamed-chunk-17"},{"row":178,"row_count":1,"visible":true,"expansion_state":0,"options":[],"document_id":null,"chunk_id":"czoqfgmjdk48u","chunk_label":"unnamed-chunk-18"}],"doc_write_time":1739826122}