{"chunk_definitions":[{"chunk_id":"cd8l43s0ba6wq","expansion_state":0,"options":[],"row":11,"row_count":1,"visible":true},{"chunk_id":"c1gsuuqey3k98","expansion_state":0,"options":[],"row":16,"row_count":1,"visible":true},{"chunk_id":"clk2zts55oejr","expansion_state":0,"options":[],"row":20,"row_count":1,"visible":true},{"chunk_id":"c5afhucuqpgae","expansion_state":0,"options":[],"row":25,"row_count":1,"visible":true},{"chunk_id":"cxqupneceaxxo","expansion_state":0,"options":[],"row":30,"row_count":1,"visible":true},{"chunk_id":"cg4otpyfgf7zi","expansion_state":0,"options":[],"row":35,"row_count":1,"visible":true},{"chunk_id":"csyo2azg94888","expansion_state":0,"options":[],"row":39,"row_count":1,"visible":true},{"chunk_id":"ctxpvndmsavwo","expansion_state":0,"options":[],"row":44,"row_count":1,"visible":true},{"chunk_id":"crfn6em11n7n9","expansion_state":0,"options":[],"row":48,"row_count":1,"visible":true},{"chunk_id":"cn753z7465ivn","expansion_state":0,"options":[],"row":52,"row_count":1,"visible":true},{"chunk_id":"ciamplsltqpx7","expansion_state":0,"options":[],"row":56,"row_count":1,"visible":true},{"chunk_id":"cl42rcrg8l824","expansion_state":0,"options":[],"row":66,"row_count":1,"visible":true}],"doc_write_time":1583115692.68542}
